README.md
setup.cfg
setup.py
xray_ot/__init__.py
xray_ot/binary_propagator.py
xray_ot/connection.py
xray_ot/constants.py
xray_ot/encoder.py
xray_ot/rand.py
xray_ot/recorder.py
xray_ot/settings.py
xray_ot/text_propagator.py
xray_ot/tracer.py
xray_ot/translator/__init__.py
xray_ot/translator/ot_types.py
xray_ot/translator/translator.py
xray_ot/translator/components/__init__.py
xray_ot/translator/components/db.py
xray_ot/translator/components/http.py
xray_ot/translator/tests/__init__.py
xray_ot/translator/tests/test_translator.py
xray_python_opentracing_fork.egg-info/PKG-INFO
xray_python_opentracing_fork.egg-info/SOURCES.txt
xray_python_opentracing_fork.egg-info/dependency_links.txt
xray_python_opentracing_fork.egg-info/requires.txt
xray_python_opentracing_fork.egg-info/top_level.txt