Metadata-Version: 1.2
Name: xray-python-opentracing-fork
Version: 0.0.4
Summary: AWS X-Ray Python OpenTracing Implementation
Home-page: UNKNOWN
Author: Jeremy Apthorp <nornagon@nornagon.net>
Maintainer: KOCAK Mikail <hello@vanille.bid>
License: UNKNOWN
Keywords: opentracing,aws,xray,awsxray,traceguide,tracing,microservices,distributed
Platform: UNKNOWN
Classifier: Operating System :: OS Independent
Classifier: Programming Language :: Python :: 3.8
Classifier: Programming Language :: Python :: 3.9
